polars_array_algorithms-0.1.1.dist-info/METADATA
polars_array_algorithms-0.1.1.dist-info/WHEEL
polars_array_algorithms-0.1.1.dist-info/licenses/LICENSE
polars_array_algorithms/__init__.py
polars_array_algorithms/_internal.pyd
polars_array_algorithms/_internal.pyi
polars_array_algorithms/typing.py
polars_array_algorithms-0.1.1.dist-info/RECORD
