Metadata-Version: 2.4
Name: polars-array-algorithms
Version: 0.1.1
Classifier: Programming Language :: Rust
Classifier: Programming Language :: Python :: Implementation :: CPython
Classifier: Programming Language :: Python :: Implementation :: PyPy
License-File: LICENSE
Summary: Rust-accelerated array algorithms for Polars DataFrames.
Requires-Python: >=3.8
Project-URL: Homepage, https://github.com/Sumanth-NR/polars_array_algorithms
